<GameData>
	<Language_en_US>
		<!-- Jaxian Civ -->
		<Row Tag="TXT_KEY_CIV_TADC3_ADJECTIVE">
			<Text>Jaxian</Text>
		</Row>
		<Row Tag="TXT_KEY_CIV_TADC3_DESC">
			<Text>The House of Jax</Text>
		</Row>
		<Row Tag="TXT_KEY_CIV_TADC3_SHORT_DESC">
			<Text>House of Jax</Text>
		</Row>
		<Row Tag="TXT_KEY_CIV5_TADC3_DOM">
			<Text>...</Text>
		</Row>


		<!-- Jaxian Civlopedia (Civ) -->
		<Row Tag="TXT_KEY_CIV5_TADC3_HEADING_1">
			<Text>About The House of Jax</Text>
		</Row>
		<Row Tag="TXT_KEY_CIV5_TADC3_TEXT_1">
			<Text>...</Text>
		</Row>
		<Row Tag="TXT_KEY_CIV5_TADC3_HEADING_2">
			<Text>How Did He Arrive Here?</Text>
		</Row>
		<Row Tag="TXT_KEY_CIV5_TADC3_TEXT_2">
			<Text>...</Text>
		</Row>


		<!-- Jaxian Civlopedia (Leader) -->
		<Row Tag="TXT_KEY_CIVILOPEDIA_LEADERS_TADC3_JAX_HEADING_1">
			<Text>About Jax</Text>
		</Row>
		<Row Tag="TXT_KEY_CIVILOPEDIA_LEADERS_TADC3_JAX_TEXT_1">
			<Text>...</Text>
		</Row>
		<Row Tag="TXT_KEY_CIVILOPEDIA_LEADERS_TADC3_JAX_LIVED">
			<Text>?? - ?? AD</Text>
		</Row>
		<Row Tag="TXT_KEY_CIVILOPEDIA_LEADERS_TADC3_JAX_NAME">
			<Text>Jax</Text>
		</Row>
		<Row Tag="TXT_KEY_CIVILOPEDIA_LEADERS_TADC3_JAX_SUBTITLE">
			<Text>...</Text>
		</Row>
		<Row Tag="TXT_KEY_LEADER_TADC3_JAX">
			<Text>Jax</Text>
		</Row>


		<!-- Jaxian Unique Trait -->
		<Row Tag="TXT_KEY_TRAIT_ASSEMBLY_LINE_SHORT">
			<Text>Assembly Line</Text>
		</Row>
		<Row Tag="TXT_KEY_TRAIT_ASSEMBLY_LINE">
			<Text>+1 [ICON_PRODUCTION] Production from Specialists. Workshops and Factories provide +1 [ICON_FOOD] Food.</Text>
		</Row>
		<!-- Jaxian Unique Unit -->
		<Row Tag="TXT_KEY_UNIT_JAXIAN_SHOTGUNNER">
			<Text>Shotgunner</Text>
		</Row>
		<Row Tag="TXT_KEY_UNIT_HELP_JAXIAN_SHOTGUNNER">
			<Text>...</Text>
		</Row>
		<Row Tag="TXT_KEY_CIV5_JAXIAN_SHOTGUNNER_TEXT">
			<Text>Pilfered from the Candy Canyon Kingdom, the design of this shotgun is rudimentary but effective.</Text>
		</Row>
		<Row Tag="TXT_KEY_UNIT_JAXIAN_SHOTGUNNER_STRATEGY">
			<Text>The Shotgunner is the Jaxian unique unit, replacing the Riflemen. It possesses a promotion that provides 16% extra defence from ranged sources and allows the unit to move after attacking.</Text>
		</Row>
		<!-- Jaxian Unique Building -->
		<Row Tag="TXT_KEY_BUILDING_TADC3_GLADIATOR_ARENA">
			<Text>Gladiator Arena</Text>
		</Row>
		<Row Tag="TXT_KEY_BUILDING_TADC3_GLADIATOR_ARENA_STRATEGY">
			<Text>Provides +1 [ICON_CULTURE] Culture and grants +10 XP to Land Units created in this city. Requires no [ICON_GOLD] Gold maintenance.</Text>
		</Row>
		<Row Tag="TXT_KEY_CIV5_BUILDINGS_TADC3_GLADIATOR_ARENA_TEXT">
			<Text>Upon being presented with the idea to build a Zoo in the empire by his advisors, Jax shuddered at the thought of seeing wholesome animals in his cities. During his time at the Digital Circus, Jax had made clear he believes all things cute and peaceful to be... completely boring. And so, Jax commissions a series of Gladiator Arenas across the empire to test the mettle of his military and provide entertainment at the same time.</Text>
		</Row>

		<!-- Jaxian Unique Promotions -->
		<Row Tag="TXT_KEY_PROMOTION_EDIBLE_AMMO">
			<Text>Edible Ammo</Text>
		</Row>
		<Row Tag="TXT_KEY_PROMOTION_EDIBLE_AMMO_HELP">
			<Text>Shotgunners heal 20 Damage when it kills a non-barbarian unit. Pillaging has zero movement cost.</Text>
		</Row>
		<Row Tag="TXT_KEY_PEDIA_PROMOTION_EDIBLE_AMMO">
			<Text>Edible Ammo</Text>
		</Row>

		<!-- Jaxian Cities (Naming Scheme: TODO) -->


		<!-- Jaxian Spies -->
		<Row Tag="TXT_KEY_SPY_NAME_TADC3_0">
			<Text>...</Text>
		</Row>
		<Row Tag="TXT_KEY_SPY_NAME_TADC3_1">
			<Text>...</Text>
		</Row>
		<Row Tag="TXT_KEY_SPY_NAME_TADC3_2">
			<Text>...</Text>
		</Row>
		<Row Tag="TXT_KEY_SPY_NAME_TADC3_3">
			<Text>...</Text>
		</Row>
		<Row Tag="TXT_KEY_SPY_NAME_TADC3_4">
			<Text>...</Text>
		</Row>
		<Row Tag="TXT_KEY_SPY_NAME_TADC3_5">
			<Text>...</Text>
		</Row>
		<Row Tag="TXT_KEY_SPY_NAME_TADC3_6">
			<Text>...</Text>
		</Row>
		<Row Tag="TXT_KEY_SPY_NAME_TADC3_7">
			<Text>...</Text>
		</Row>
		<Row Tag="TXT_KEY_SPY_NAME_TADC3_8">
			<Text>...</Text>
		</Row>
		<Row Tag="TXT_KEY_SPY_NAME_TADC3_9">
			<Text>...</Text>
		</Row>
	</Language_en_US>
</GameData>